README.md
setup.cfg
setup.py
LAVAPI/LAVAPI.py
LAVAPI/__init__.py
LAVAPI.egg-info/PKG-INFO
LAVAPI.egg-info/SOURCES.txt
LAVAPI.egg-info/dependency_links.txt
LAVAPI.egg-info/requires.txt
LAVAPI.egg-info/top_level.txt