Metadata-Version: 2.1
Name: LAVAPI
Version: 1.0
Summary: The LAVAPI library was created in order to facilitate work with the official API of the LAVA payment system.It presents all the methods present in the official documentation.
Home-page: https://github.com/DIMFLIX-OFFICIAL/LAVAPI
Download-URL: https://github.com//DIMFLIX-OFFICIAL/LAVAPI/archive/refs/heads/main.zip
Author: DIMFLIX
Author-email: dimflix.official@gmail.ru
License: MIT License
Classifier: Operating System :: OS Independent
Classifier: Intended Audience :: End Users/Desktop
Classifier: Intended Audience :: Developers
Classifier: Programming Language :: Python
Classifier: Programming Language :: Python :: 3
Classifier: Programming Language :: Python :: 3.6
Classifier: Programming Language :: Python :: 3.7
Classifier: Programming Language :: Python :: 3.8
Classifier: Programming Language :: Python :: 3.9
Classifier: Programming Language :: Python :: 3.10
Classifier: Programming Language :: Python :: 3.11
Classifier: Programming Language :: Python :: Implementation :: PyPy
Classifier: Programming Language :: Python :: Implementation :: CPython
